arangoasync/__init__.py
arangoasync/aql.py
arangoasync/auth.py
arangoasync/backup.py
arangoasync/client.py
arangoasync/cluster.py
arangoasync/collection.py
arangoasync/compression.py
arangoasync/connection.py
arangoasync/cursor.py
arangoasync/database.py
arangoasync/errno.py
arangoasync/exceptions.py
arangoasync/executor.py
arangoasync/foxx.py
arangoasync/graph.py
arangoasync/http.py
arangoasync/job.py
arangoasync/logger.py
arangoasync/replication.py
arangoasync/request.py
arangoasync/resolver.py
arangoasync/response.py
arangoasync/result.py
arangoasync/serialization.py
arangoasync/typings.py
arangoasync/version.py
python_arango_async-1.1.0.dist-info/licenses/LICENSE
python_arango_async-1.1.0.dist-info/METADATA
python_arango_async-1.1.0.dist-info/WHEEL
python_arango_async-1.1.0.dist-info/top_level.txt
python_arango_async-1.1.0.dist-info/RECORD
