Metadata-Version: 2.4
Name: python-arango-async
Version: 1.1.0
Summary: Async Python Driver for ArangoDB
Author-email: Alexandru Petenchea <alexandru.petenchea@arangodb.com>, Anthony Mahanna <anthony.mahanna@arangodb.com>
Maintainer-email: Alexandru Petenchea <alexandru.petenchea@arangodb.com>, Anthony Mahanna <anthony.mahanna@arangodb.com>
License-Expression: MIT
Project-URL: homepage, https://github.com/arangodb/python-arango-async
Keywords: arangodb,python,driver,async
Classifier: Intended Audience :: Developers
Classifier: Natural Language :: English
Classifier: Operating System :: OS Independent
Classifier: Programming Language :: Python :: 3
Classifier: Programming Language :: Python :: 3.10
Classifier: Programming Language :: Python :: 3.11
Classifier: Programming Language :: Python :: 3.12
Classifier: Programming Language :: Python :: 3.13
Classifier: Topic :: Documentation :: Sphinx
Classifier: Typing :: Typed
Requires-Python: >=3.10
License-File: LICENSE
Requires-Dist: packaging>=23.1
Requires-Dist: aiohttp>=3.9
Requires-Dist: multidict>=6.0
Requires-Dist: pyjwt>=2.10.0
Provides-Extra: dev
Requires-Dist: aiofiles>=24.1.0; extra == "dev"
Requires-Dist: black==26.1.0; extra == "dev"
Requires-Dist: flake8==7.3.0; extra == "dev"
Requires-Dist: isort>=5.10.1; extra == "dev"
Requires-Dist: mypy==1.15.0; extra == "dev"
Requires-Dist: pre-commit>=3.7; extra == "dev"
Requires-Dist: pytest>=8.2; extra == "dev"
Requires-Dist: pytest-asyncio>=0.23.8; extra == "dev"
Requires-Dist: pytest-cov>=5.0; extra == "dev"
Requires-Dist: sphinx>=7.3; extra == "dev"
Requires-Dist: sphinx_rtd_theme>=2.0; extra == "dev"
Requires-Dist: allure-pytest>=2.15; extra == "dev"
Requires-Dist: types-setuptools; extra == "dev"
Dynamic: license-file
